setup.py
joaye_probability/Binomialdistribution.py
joaye_probability/Gaussiandistribution.py
joaye_probability/Generaldistribution.py
joaye_probability/__init__.py
joaye_probability.egg-info/PKG-INFO
joaye_probability.egg-info/SOURCES.txt
joaye_probability.egg-info/dependency_links.txt
joaye_probability.egg-info/not-zip-safe
joaye_probability.egg-info/top_level.txt