Metadata-Version: 1.0
Name: joaye-probability
Version: 1.1
Summary: Gaussian and Binomial Distribution
Home-page: UNKNOWN
Author: UNKNOWN
Author-email: joeypewpew@gmail.com
License: UNKNOWN
Platform: UNKNOWN
